{
    "NORMAL": {
        "color": "0xffffff",
        "thumbnail_url": "https://i.postimg.cc/sxfQdw2X/image.png"
    },

    "WINDY": {
        "color": "0x9ae5ff",
        "duration": 120,
        "thumbnail_url": "https://i.postimg.cc/6qPH4wy6/image.png"
    },
    "RAINY": {
        "color": "0x027cbd",
        "duration": 120,
        "thumbnail_url": "https://static.wikia.nocookie.net/sol-rng/images/e/ec/Rainy.png"
    },
    "SNOWY": {
        "color": "0xDceff9",
        "duration": 120,
        "thumbnail_url": "https://i.postimg.cc/ydc0ZN1f/image.png"
    },
    "SAND STORM": {
        "color": "0x8F7057",
        "duration": 600,
        "thumbnail_url": "https://i.postimg.cc/3JyL25Kz/image.png"
    },
    "HELL": {
        "color": "0xff4719",
        "duration": 660,
        "thumbnail_url": "https://i.postimg.cc/hGC5xNyY/image.png"
    },
    "STARFALL": {
        "color": "0x011ab7",
        "duration": 600,
        "thumbnail_url": "https://i.postimg.cc/1t0dY4J8/image.png"
    },
    "CORRUPTION": {
        "color": "0x6d32a8",
        "duration": 660,
        "thumbnail_url": "https://i.postimg.cc/ncZQ84Dh/image.png"
    },
    "NULL": {
        "color": "0x838383",
        "duration": 90,
        "thumbnail_url": "https://static.wikia.nocookie.net/sol-rng/images/f/fc/NULLLL.png"
    },
    "GLITCHED": {
        "color": "0xbfff00",
        "duration": 164,
        "thumbnail_url": "https://i.postimg.cc/W3Lhtn5g/image.png"
    },
    "DREAMSPACE": {
        "color": "0xea9dda",
        "duration": 130,
        "thumbnail_url": "https://i.postimg.cc/rFjCcW3w/image.png"
    }
}